[
  {
    "file_name": "4.pdf",
    "uploaded_at": "2025-07-19T13:58:53.178044",
    "entities": [
      {
        "type": "generic_entities",
        "mention_text": "",
        "confidence": 0.0
      }
    ]
  },
  {
    "file_name": "3.jpg",
    "uploaded_at": "2025-07-19T14:00:51.578622",
    "entities": [
      {
        "type": "generic_entities",
        "mention_text": "",
        "confidence": 0.0
      }
    ]
  },
  {
    "file_name": "4.pdf",
    "uploaded_at": "2025-07-19T14:06:58.649974",
    "iin": "211140026677",
    "bic": "HSBKKZKX",
    "total": "171360,00\n18360,00\n",
    "date": null,
    "items": [
      {
        "name": "Сумма",
        "qty": "1",
        "price": "171360,00\n"
      },
      {
        "name": "на сумму",
        "qty": "171",
        "price": "360,00"
      }
    ]
  },
  {
    "file_name": "4.pdf",
    "uploaded_at": "2025-07-19T14:14:51.310218",
    "text": "Внимание! Оплата данного счета означает согласие с условиями поставки товара. Уведомление об оплате\nобязательно, в противном случае не гарантируется наличие товара на складе. Товар отпускается по факту\nприхода денег на p/с Поставщика, самовывозом, при наличии доверенности и документов удостоверяющих\nЛИЧНОСТЬ.\nИИК\nКбе\nОбразец платежного поручения\n|Бенефициар:\nTOO <<Frozen Fruit>>\nБИН: 211140026677\nБанк бенефициара:\nАО \"Народный Банк Казахстана\" г. г. Алматы\nKZ12601A861001719591\n17\nБИК\nКод назначения платежа\nHSBKKZKX\n710\nСчет на оплату № 2877 от 10 октября 2023 г.\nПоставщик:\nБИН / ИИН 211140026677,TOO «Frozen Fruit»,050017, Республика Казахстан, Жетысуский\nрайон, город Алматы, улица Жадаукок, дом № 26В, тел.: 87778242842\nПокупатель: БИН / ИИН 220440052824,TOO \"COFFEEDAY WORLD\",Астана, улица Достық, дом 2\nДоговор:\nДоговор № 23/01-148 от 19.05.2023г.\nNo\nКод\n00000005170\nНаименование\nМолоко 3,2% \" Эконива\", 1,0 л\nКол-во Ед.\n408,000 шт\nЦена\n420,00\nСумма\n1\n171 360,00\nИтого:\n171 360,00\n18 360,00\nВ том числе НДС:\nВсего наименований 1, на сумму 171 360,00 KZT\nВсего к оплате: Сто семьдесят одна тысяча триста шестьдесят тенге 00 тиын\nИсполнитель\n||\n",
    "items": [
      [
        "1",
        "00000005170",
        "Молоко 3,2% \" Эконива\", 1,0 л",
        "408,000",
        "шт",
        "420,00",
        "171 360,00"
      ],
      [
        "TOO <<Frozen Fruit>>",
        "17"
      ],
      [
        "БИН: 211140026677",
        "KZ12601A861001719591"
      ],
      [
        "Банк бенефициара:",
        "БИК\nКод назначения платежа"
      ],
      [
        "АО \"Народный Банк Казахстана\" г. г. Алматы",
        "HSBKKZKX\n710"
      ],
      [
        "Покупатель:",
        "БИН / ИИН 220440052824,TOO \"COFFEEDAY WORLD\",Астана, улица Достық, дом 2"
      ],
      [
        "Договор:",
        "Договор № 23/01-148 от 19.05.2023г."
      ]
    ],
    "extracted_fields": {
      "iin": "бенефиц",
      "bic": "HSB",
      "total": "Всего",
      "date": "ивном случае не гарантируется наличие товара на складе. Товар отпускается по факту\nприхода денег на p/с Поставщика, самовывозом, при наличии доверенности и документов удостоверяющих\nЛИЧНОСТЬ.\nИИК\nКбе\nОбразец платежного поручения\n|Бенефициар:\nTOO <<Frozen Fruit>>\nБИН: 211140026677\nБанк бенефициара:\nАО \"Народный Банк Казахстана\""
    }
  },
  {
    "file_name": "4.pdf",
    "uploaded_at": "2025-07-20T07:28:58.618525",
    "text": "Внимание! Оплата данного счета означает согласие с условиями поставки товара. Уведомление об оплате\nобязательно, в противном случае не гарантируется наличие товара на складе. Товар отпускается по факту\nприхода денег на p/с Поставщика, самовывозом, при наличии доверенности и документов удостоверяющих\nЛИЧНОСТЬ.\nИИК\nКбе\nОбразец платежного поручения\n|Бенефициар:\nTOO <<Frozen Fruit>>\nБИН: 211140026677\nБанк бенефициара:\nАО \"Народный Банк Казахстана\" г. г. Алматы\nKZ12601A861001719591\n17\nБИК\nКод назначения платежа\nHSBKKZKX\n710\nСчет на оплату № 2877 от 10 октября 2023 г.\nПоставщик:\nБИН / ИИН 211140026677,TOO «Frozen Fruit»,050017, Республика Казахстан, Жетысуский\nрайон, город Алматы, улица Жадаукок, дом № 26В, тел.: 87778242842\nПокупатель: БИН / ИИН 220440052824,TOO \"COFFEEDAY WORLD\",Астана, улица Достық, дом 2\nДоговор:\nДоговор № 23/01-148 от 19.05.2023г.\nNo\nКод\n00000005170\nНаименование\nМолоко 3,2% \" Эконива\", 1,0 л\nКол-во Ед.\n408,000 шт\nЦена\n420,00\nСумма\n1\n171 360,00\nИтого:\n171 360,00\n18 360,00\nВ том числе НДС:\nВсего наименований 1, на сумму 171 360,00 KZT\nВсего к оплате: Сто семьдесят одна тысяча триста шестьдесят тенге 00 тиын\nИсполнитель\n||\n",
    "items": [
      [
        "1",
        "00000005170",
        "Молоко 3,2% \" Эконива\", 1,0 л",
        "408,000",
        "шт",
        "420,00",
        "171 360,00"
      ],
      [
        "TOO <<Frozen Fruit>>",
        "17"
      ],
      [
        "БИН: 211140026677",
        "KZ12601A861001719591"
      ],
      [
        "Банк бенефициара:",
        "БИК\nКод назначения платежа"
      ],
      [
        "АО \"Народный Банк Казахстана\" г. г. Алматы",
        "HSBKKZKX\n710"
      ],
      [
        "Покупатель:",
        "БИН / ИИН 220440052824,TOO \"COFFEEDAY WORLD\",Астана, улица Достық, дом 2"
      ],
      [
        "Договор:",
        "Договор № 23/01-148 от 19.05.2023г."
      ]
    ],
    "extracted_fields": {
      "iin": "бенефиц",
      "bic": "HSB",
      "total": "Всего",
      "date": "ивном случае не гарантируется наличие товара на складе. Товар отпускается по факту\nприхода денег на p/с Поставщика, самовывозом, при наличии доверенности и документов удостоверяющих\nЛИЧНОСТЬ.\nИИК\nКбе\nОбразец платежного поручения\n|Бенефициар:\nTOO <<Frozen Fruit>>\nБИН: 211140026677\nБанк бенефициара:\nАО \"Народный Банк Казахстана\""
    }
  },
  {
    "file_name": "3.jpg",
    "uploaded_at": "2025-07-20T07:35:12.098054",
    "text": "Внимание! Счет действителен до 10.10 2023\nОпита данного созначает согласие с условиями поставки товараУводомление об оплате обязательно в \nпротивном случае не гарантируетсяналичие товара на складе. Товар отпускается \nпо факту прихода денегна р/с Поставщикозом, \nпри наличии доверенности\nи документов удостоверяющих личность\nAO \"KASPI BANK\"\nОбразец заполнения платежного поручения\nБИК CASPKZKA\nCy. No\nБанк получателя\nИИН/БИН 970119300335\nИП CHUNKY COOKIES\nC4. No\nKZ64722S000010785672\nкБе\n19\nA\n+\nКод наз. пл\nкод\nC4231000010014800006\nПолучатель\nОплата по реализации товаров и услуг №1-3657\nНазначение пл\nСчет на оплату № 1-1480 от 10 октября 2023 г.\nПоставщик ИП CHUNKY COOKIES, БИН / ИИН 970119300335, Республика Казахстан, г. Алматы, 2 МКР, дом 38, кв/офис 28\nПокупатель Coffeeday World TOO, БИН / ИИН 220440052824, TPK MEGA Раrkпроспект Сейфуллина, 483\nКоличество\nЦена\nСумма\n10\nШТ\n300,00\n3 000.00\n10\nWIT\n300,00\n3 000,00\n3000.00\n10\nWIT\n300,00\nNo\nТовары (работы, услуги)\n| Chunky с молочным шоколадом\n2 Chunky c молочным шоколадом и грецким орехом\n3 Chunky c Gелым шоколадом и миндальным спайсом\n4 Chunky с какао и белым шоколадом\n5 Chunky c kakao и темным шоколадом\nB Chunky\nовсяные с изюмом и грецким орехом\nПеченье Chunky Карамельное\n10\n300.00\n3 000.00\nш\nшт\n300,00\n2 100,00\n2100,00\nшт\n300,00\n300,00\n1 800.00\n8\nшт\n18 000,00\nИтого:\nБез налога (НДС)\nВсего наименований 7, на сумму 18 000,00 KZT\nВосемнадцать тысяч тенге 00 тиын\nРуководитель\nрасшифр подписи\nPECOVEA RASANGTAR FOR\nподпись\nБухгалтер\nрасшифровка подписи\nподпись\nCHUNEY\nCOOKIES\nДЛЯ НАКЛАДНЫХ\nМенеджер\nрасшифровка подписи\nподпись\n570\nWWW.VEC\n",
    "items": [
      {
        "col_0": "No",
        "col_1": "Товары (работы, услуги)",
        "col_2": "Количество",
        "col_3": "Цена",
        "col_4": "Сумма"
      },
      {
        "col_0": "|",
        "col_1": "Chunky с молочным шоколадом",
        "col_2": "10\nШТ",
        "col_3": "300,00",
        "col_4": "3 000.00"
      },
      {
        "col_0": "2",
        "col_1": "Chunky c молочным шоколадом и грецким орехом",
        "col_2": "10\nWIT",
        "col_3": "300,00",
        "col_4": "3 000,00\n3000.00"
      },
      {
        "col_0": "3",
        "col_1": "Chunky c Gелым шоколадом и миндальным спайсом",
        "col_2": "10\nWIT",
        "col_3": "300,00",
        "col_4": "3 000.00"
      },
      {
        "col_0": "4",
        "col_1": "Chunky с какао и белым шоколадом",
        "col_2": "10",
        "col_3": "300,00",
        "col_4": "2 100,00"
      },
      {
        "col_0": "5",
        "col_1": "Chunky c kakao и темным шоколадом",
        "col_2": "шт",
        "col_3": "300,00\n300,00",
        "col_4": "2100,00"
      },
      {
        "col_1": "Печенье Chunky Карамельное"
      },
      {
        "col_3": "Итого:",
        "col_4": "18 000,00"
      },
      {
        "col_0": "Руководитель\nрасшифр подписи\nPECOVEA RASANGTAR FOR\nподпись\nБухгалтер\nрасшифровка подписи\nподпись\nCHUNEY\nCOOKIES\nДЛЯ НАКЛАДНЫХ\nМенеджер\nрасшифровка подписи\nподпись"
      },
      {
        "col_0": "AO \"KASPI BANK\"\nОбразец заполнения платежного поручения\nБИК CASPKZKA\nCy. No\nБанк получателя\nИИН/БИН 970119300335"
      },
      {
        "col_0": "ИП CHUNKY COOKIES"
      },
      {
        "col_0": "A\n+\nКод наз. пл\nкод\nC4231000010014800006"
      }
    ],
    "extracted_fields": {
      "iin": "COO",
      "bic": "получ",
      "total": "с",
      "date": "ивном случае не гарантируетсяналичие товара на складе. Товар отпускается \nпо факту прихода денегна р/с Поставщикозом, \nпри наличии доверенности\nи документов удостоверяющих личность\nAO \"KASPI BANK\"\nОбразец заполнения платежного поручения\nБИК CASPKZKA\nCy. No\nБанк получателя\nИИН/БИН 970119300335\nИП CHUNKY COOKIES\nC4. No\nKZ64722S000010785672\nкБе\n19\nA\n+\nКод наз. пл\nкод\nC4231000010014800006\nПолучатель\nОплата по реализации товаров и услуг №1-3657\nНазначение пл\nСчет на оплату № 1-1480 от 10 октября 2023"
    }
  },
  {
    "file_name": "4.pdf",
    "uploaded_at": "2025-07-23T12:09:19.062231",
    "text": "Внимание! Оплата данного счета означает согласие с условиями поставки товара. Уведомление об оплате\nобязательно, в противном случае не гарантируется наличие товара на складе. Товар отпускается по факту\nприхода денег на p/с Поставщика, самовывозом, при наличии доверенности и документов удостоверяющих\nЛИЧНОСТЬ.\nИИК\nКбе\nОбразец платежного поручения\n|Бенефициар:\nTOO <<Frozen Fruit>>\nБИН: 211140026677\nБанк бенефициара:\nАО \"Народный Банк Казахстана\" г. г. Алматы\nKZ12601A861001719591\n17\nБИК\nКод назначения платежа\nHSBKKZKX\n710\nСчет на оплату № 2877 от 10 октября 2023 г.\nПоставщик:\nБИН / ИИН 211140026677,TOO «Frozen Fruit»,050017, Республика Казахстан, Жетысуский\nрайон, город Алматы, улица Жадаукок, дом № 26В, тел.: 87778242842\nПокупатель: БИН / ИИН 220440052824,TOO \"COFFEEDAY WORLD\",Астана, улица Достық, дом 2\nДоговор:\nДоговор № 23/01-148 от 19.05.2023г.\nNo\nКод\n00000005170\nНаименование\nМолоко 3,2% \" Эконива\", 1,0 л\nКол-во Ед.\n408,000 шт\nЦена\n420,00\nСумма\n1\n171 360,00\nИтого:\n171 360,00\n18 360,00\nВ том числе НДС:\nВсего наименований 1, на сумму 171 360,00 KZT\nВсего к оплате: Сто семьдесят одна тысяча триста шестьдесят тенге 00 тиын\nИсполнитель\n||\n",
    "items": [
      {
        "col_0": "No",
        "col_1": "Код",
        "col_2": "Наименование",
        "col_3": "Кол-во",
        "col_4": "Ед.",
        "col_5": "Цена",
        "col_6": "Сумма"
      },
      {
        "col_0": "1",
        "col_1": "00000005170",
        "col_2": "Молоко 3,2% \" Эконива\", 1,0 л",
        "col_3": "408,000",
        "col_4": "шт",
        "col_5": "420,00",
        "col_6": "171 360,00"
      },
      {
        "col_0": "|Бенефициар:",
        "col_1": "ИИК\nКбе"
      },
      {
        "col_0": "TOO <<Frozen Fruit>>",
        "col_1": "17"
      },
      {
        "col_0": "БИН: 211140026677",
        "col_1": "KZ12601A861001719591"
      },
      {
        "col_0": "Банк бенефициара:",
        "col_1": "БИК\nКод назначения платежа"
      },
      {
        "col_0": "АО \"Народный Банк Казахстана\" г. г. Алматы",
        "col_1": "HSBKKZKX\n710"
      },
      {
        "col_0": "Поставщик:",
        "col_1": "БИН / ИИН 211140026677,TOO «Frozen Fruit»,050017, Республика Казахстан, Жетысуский\nрайон, город Алматы, улица Жадаукок, дом № 26В, тел.: 87778242842"
      },
      {
        "col_0": "Покупатель:",
        "col_1": "БИН / ИИН 220440052824,TOO \"COFFEEDAY WORLD\",Астана, улица Достық, дом 2"
      },
      {
        "col_0": "Договор:",
        "col_1": "Договор № 23/01-148 от 19.05.2023г."
      }
    ],
    "extracted_fields": {
      "iin": "бенефиц",
      "bic": "HSB",
      "total": "Всего",
      "date": "ивном случае не гарантируется наличие товара на складе. Товар отпускается по факту\nприхода денег на p/с Поставщика, самовывозом, при наличии доверенности и документов удостоверяющих\nЛИЧНОСТЬ.\nИИК\nКбе\nОбразец платежного поручения\n|Бенефициар:\nTOO <<Frozen Fruit>>\nБИН: 211140026677\nБанк бенефициара:\nАО \"Народный Банк Казахстана\""
    }
  },
  {
    "file_name": "4.pdf",
    "uploaded_at": "2025-07-23T12:10:03.511803",
    "text": "Внимание! Оплата данного счета означает согласие с условиями поставки товара. Уведомление об оплате\nобязательно, в противном случае не гарантируется наличие товара на складе. Товар отпускается по факту\nприхода денег на p/с Поставщика, самовывозом, при наличии доверенности и документов удостоверяющих\nЛИЧНОСТЬ.\nИИК\nКбе\nОбразец платежного поручения\n|Бенефициар:\nTOO <<Frozen Fruit>>\nБИН: 211140026677\nБанк бенефициара:\nАО \"Народный Банк Казахстана\" г. г. Алматы\nKZ12601A861001719591\n17\nБИК\nКод назначения платежа\nHSBKKZKX\n710\nСчет на оплату № 2877 от 10 октября 2023 г.\nПоставщик:\nБИН / ИИН 211140026677,TOO «Frozen Fruit»,050017, Республика Казахстан, Жетысуский\nрайон, город Алматы, улица Жадаукок, дом № 26В, тел.: 87778242842\nПокупатель: БИН / ИИН 220440052824,TOO \"COFFEEDAY WORLD\",Астана, улица Достық, дом 2\nДоговор:\nДоговор № 23/01-148 от 19.05.2023г.\nNo\nКод\n00000005170\nНаименование\nМолоко 3,2% \" Эконива\", 1,0 л\nКол-во Ед.\n408,000 шт\nЦена\n420,00\nСумма\n1\n171 360,00\nИтого:\n171 360,00\n18 360,00\nВ том числе НДС:\nВсего наименований 1, на сумму 171 360,00 KZT\nВсего к оплате: Сто семьдесят одна тысяча триста шестьдесят тенге 00 тиын\nИсполнитель\n||\n",
    "items": [
      {
        "col_0": "No",
        "col_1": "Код",
        "col_2": "Наименование",
        "col_3": "Кол-во",
        "col_4": "Ед.",
        "col_5": "Цена",
        "col_6": "Сумма"
      },
      {
        "col_0": "1",
        "col_1": "00000005170",
        "col_2": "Молоко 3,2% \" Эконива\", 1,0 л",
        "col_3": "408,000",
        "col_4": "шт",
        "col_5": "420,00",
        "col_6": "171 360,00"
      },
      {
        "col_0": "|Бенефициар:",
        "col_1": "ИИК\nКбе"
      },
      {
        "col_0": "TOO <<Frozen Fruit>>",
        "col_1": "17"
      },
      {
        "col_0": "БИН: 211140026677",
        "col_1": "KZ12601A861001719591"
      },
      {
        "col_0": "Банк бенефициара:",
        "col_1": "БИК\nКод назначения платежа"
      },
      {
        "col_0": "АО \"Народный Банк Казахстана\" г. г. Алматы",
        "col_1": "HSBKKZKX\n710"
      },
      {
        "col_0": "Поставщик:",
        "col_1": "БИН / ИИН 211140026677,TOO «Frozen Fruit»,050017, Республика Казахстан, Жетысуский\nрайон, город Алматы, улица Жадаукок, дом № 26В, тел.: 87778242842"
      },
      {
        "col_0": "Покупатель:",
        "col_1": "БИН / ИИН 220440052824,TOO \"COFFEEDAY WORLD\",Астана, улица Достық, дом 2"
      },
      {
        "col_0": "Договор:",
        "col_1": "Договор № 23/01-148 от 19.05.2023г."
      }
    ],
    "extracted_fields": {
      "iin": "бенефиц",
      "bic": "HSB",
      "total": "Всего",
      "date": "ивном случае не гарантируется наличие товара на складе. Товар отпускается по факту\nприхода денег на p/с Поставщика, самовывозом, при наличии доверенности и документов удостоверяющих\nЛИЧНОСТЬ.\nИИК\nКбе\nОбразец платежного поручения\n|Бенефициар:\nTOO <<Frozen Fruit>>\nБИН: 211140026677\nБанк бенефициара:\nАО \"Народный Банк Казахстана\""
    }
  }
]